{
	"$schema": "./node_modules/@biomejs/biome/configuration_schema.json",
	"vcs": {
		"enabled": false,
		"clientKind": "git",
		"useIgnoreFile": true
	},
	"files": {
		"ignoreUnknown": false,
		"includes": [
			"packages/*/src,test}ts",
			"packages/*/src/**/*.js",
			"packages/*/test/**/*.ts",
			"packages/*/test/**/*.js",
			"packages/*/package.json",
			"packages/*/tsconfig*.json",
			"*.ts",
			"*.js",
			"*.json"
		],
		"experimentalScannerIgnores": ["dist", "node_modules", "output"]
	},
	"formatter": {
		"enabled": true,
		"indentStyle": "tab"
	},
	"linter": {
		"enabled": true,
		"rules": {
			"recommended": true
		}
	},
	"javascript": {
		"formatter": {
			"quoteStyle": "double"
		}
	},
	"assist": {
		"enabled": true,
		"actions": {
			"source": {
				"organizeImports": "on"
			}
		}
	}
}
